shipyard_hex/__init__.py
shipyard_hex/cli/__init__.py
shipyard_hex/cli/authtest.py
shipyard_hex/cli/check_run_status.py
shipyard_hex/cli/exit_codes.py
shipyard_hex/cli/hex_run_project.py
shipyard_hex/hex.py
shipyard_hex-0.1.0.dist-info/METADATA
shipyard_hex-0.1.0.dist-info/WHEEL
shipyard_hex-0.1.0.dist-info/RECORD
