Metadata-Version: 2.1
Name: shipyard-hex
Version: 0.1.0
Summary: A local client for connecting and working with Hex
License: Apache 2.0
Author: wrp801
Author-email: wespoulsen@gmail.com
Requires-Python: >=3.7,<3.10
Classifier: License :: Other/Proprietary License
Classifier: Programming Language :: Python :: 3
Classifier: Programming Language :: Python :: 3.7
Classifier: Programming Language :: Python :: 3.8
Classifier: Programming Language :: Python :: 3.9
Requires-Dist: requests (==2.28.1)
Requires-Dist: shipyard-templates (==0.5.0a0)
Requires-Dist: shipyard-utils (==0.1.4)
